kaspi_offers_py/__init__.py
kaspi_offers_py/client.py
kaspi_offers_py/main.py
kaspi_offers_py/models.py
kaspi_offers_py-0.2.2.dist-info/METADATA
kaspi_offers_py-0.2.2.dist-info/WHEEL
kaspi_offers_py-0.2.2.dist-info/top_level.txt
kaspi_offers_py-0.2.2.dist-info/RECORD
