Metadata-Version: 2.4
Name: kaspi-offers-py
Version: 0.2.2
Summary: Python client for Kaspi.kz offers API
Author: Nurzhan Aitbayev
Requires-Python: >=3.9
Requires-Dist: httpx>=0.27.0
Requires-Dist: httpx-retries>=0.4.0
Provides-Extra: dev
Requires-Dist: pytest>=7.0; extra == "dev"
Requires-Dist: pytest-asyncio>=0.21.0; extra == "dev"
Requires-Dist: pytest-httpx>=0.30.0; extra == "dev"
Requires-Dist: pytest-cov>=4.0.0; extra == "dev"
